{"P7": {"labels": ["blog"], "postTitle": "\u6240\u4ee5\u8bf4\u90e8\u7f72\u8fd9\u4e2a\u7f51\u7ad9\u82b1\u4e86\u6211\u6574\u6574\u4e00\u5929\uff01\u2014\u2014docker\u306e\u5b66\u4e60\u65e5\u8bb0", "postUrl": "post/suo-yi-shuo-bu-shu-zhe-ge-wang-zhan-hua-le-wo-zheng-zheng-yi-tian-%EF%BC%81%E2%80%94%E2%80%94docker%E3%81%AE-xue-xi-ri-ji.html", "createdDate": "2025-02-15", "dateLabelColor": "#0969da"}, "P6": {"labels": ["blog"], "postTitle": "\u7c7bUbuntu\u2014\u2014\u6211\u662f\u5982\u4f55\u7ecf\u5386\u4e86\u91cd\u91cd\u5931\u8d25\u6700\u7ec8\u53bb\u9009\u62e9Lubuntu\u7684\ud83d\ude2d", "postUrl": "post/lei-Ubuntu%E2%80%94%E2%80%94-wo-shi-ru-he-jing-li-le-zhong-zhong-shi-bai-zui-zhong-qu-xuan-ze-Lubuntu-de-%F0%9F%98%AD.html", "createdDate": "2025-02-15", "dateLabelColor": "#0969da"}, "P5": {"labels": ["blog"], "postTitle": "Unity\u7684\u521d\u6b65\u4f7f\u7528\u4e0e\u5b66\u4e60\u2014\u20142D\u6a2a\u677f\u52a8\u4f5c\u95ef\u5173\u6e38\u620f\u5236\u4f5c\u5b9e\u8df5\ud83c\udfae\ud83d\udd79", "postUrl": "post/Unity-de-chu-bu-shi-yong-yu-xue-xi-%E2%80%94%E2%80%942D-heng-ban-dong-zuo-chuang-guan-you-xi-zhi-zuo-shi-jian-%F0%9F%8E%AE%F0%9F%95%B9.html", "createdDate": "2025-02-15", "dateLabelColor": "#0969da"}, "P4": {"labels": ["blog"], "postTitle": "\u5173\u4e8e\u533a\u5757\u94fe\u7684\u4e00\u4e9b\u57fa\u672c\u4e86\u89e3\u4e0e\u76f8\u5173\u6280\u672f\u7684\u5e94\u7528\u6027\u601d\u7d22", "postUrl": "post/guan-yu-qu-kuai-lian-de-yi-xie-ji-ben-le-jie-yu-xiang-guan-ji-shu-de-ying-yong-xing-si-suo.html", "createdDate": "2025-02-15", "dateLabelColor": "#0969da"}, "P2": {"labels": ["blog"], "postTitle": "\u6eda\u52a8\u6b4c\u8bcd\u5236\u4f5c\u5b9e\u8df5", "postUrl": "post/gun-dong-ge-ci-zhi-zuo-shi-jian.html", "createdDate": "2025-02-15", "dateLabelColor": "#0969da"}, "P1": {"labels": ["blog"], "postTitle": "\u4ee5\u540e\u51ed\u58f0\u97f3\u8fd8\u80fd\u76f8\u4fe1\u662f\u672c\u4eba\u5417\uff1f??\ud83d\ude3f", "postUrl": "post/yi-hou-ping-sheng-yin-huan-neng-xiang-xin-shi-ben-ren-ma-%EF%BC%9F--%F0%9F%98%BF.html", "createdDate": "2025-02-15", "dateLabelColor": "#0969da"}, "labelColorDict": {"blog": "#c2e0c6", "bug": "#d73a4a", "documentation": "#0075ca", "duplicate": "#cfd3d7", "enhancement": "#a2eeef", "good first issue": "#7057ff", "help wanted": "#008672", "invalid": "#e4e669", "question": "#d876e3", "wontfix": "#ffffff"}}